test_package/__init__.py
test_package-11.4.0.dist-info/METADATA
test_package-11.4.0.dist-info/WHEEL
test_package-11.4.0.dist-info/top_level.txt
test_package-11.4.0.dist-info/RECORD
